kevj711_superduper_sql-0.7.2.dist-info/licenses/LICENSE
superduper_sql/__init__.py
superduper_sql/data_backend.py
superduper_sql/db_helper.py
superduper_sql/field_types.py
superduper_sql/utils.py
kevj711_superduper_sql-0.7.2.dist-info/METADATA
kevj711_superduper_sql-0.7.2.dist-info/WHEEL
kevj711_superduper_sql-0.7.2.dist-info/top_level.txt
kevj711_superduper_sql-0.7.2.dist-info/RECORD
