Metadata-Version: 2.4
Name: kevj711-superduper-sql
Version: 0.7.2
Summary: `superduper_sql` is a plugin for SQL databases that allows you to use these databases as databackends for Superduper.
Maintainer-email: "superduper.io, Inc." <opensource@superduper.io>
License: 
Project-URL: homepage, https://superduper.io
Project-URL: documentation, https://docs.superduper.io/docs/intro
Project-URL: source, https://github.com/superduper-io/superduper
Keywords: databases,mongodb,data-science,machine-learning,mlops,vector-database,ai
Requires-Python: >=3.10
License-File: LICENSE
Requires-Dist: ibis-framework[sqlite]==10.4.0
Requires-Dist: click
Requires-Dist: pandas
Requires-Dist: sqlalchemy>=1.4.0
Provides-Extra: test
Dynamic: license-file
